ptrlib/__init__.py
ptrlib/algorithm/__init__.py
ptrlib/algorithm/shortestpath/__init__.py
ptrlib/algorithm/shortestpath/base.py
ptrlib/algorithm/shortestpath/shortestpath.py
ptrlib/algorithm/shortestpath/types.py
ptrlib/algorithm/shortestpath/algorithms/__init__.py
ptrlib/algorithm/shortestpath/algorithms/astar.py
ptrlib/algorithm/shortestpath/algorithms/bulkdijkstra.py
ptrlib/algorithm/shortestpath/algorithms/dijkstra.py
ptrlib/algorithm/shortestpath/algorithms/floydwarshall.py
ptrlib/algorithm/shortestpath/utils/__init__.py
ptrlib/algorithm/shortestpath/utils/lazylist.py
ptrlib/arch/__init__.py
ptrlib/arch/arm/__init__.py
ptrlib/arch/arm/archname.py
ptrlib/arch/arm/assembler.py
ptrlib/arch/arm/consts.py
ptrlib/arch/arm/disassembler.py
ptrlib/arch/arm/syscall.py
ptrlib/arch/common/__init__.py
ptrlib/arch/common/assembler.py
ptrlib/arch/common/disassembler.py
ptrlib/arch/common/ospath.py
ptrlib/arch/intel/__init__.py
ptrlib/arch/intel/archname.py
ptrlib/arch/intel/assembler.py
ptrlib/arch/intel/consts.py
ptrlib/arch/intel/cpu.py
ptrlib/arch/intel/disassembler.py
ptrlib/arch/intel/simd.py
ptrlib/arch/intel/syscall.py
ptrlib/arch/linux/__init__.py
ptrlib/arch/linux/consts.py
ptrlib/arch/linux/memory.py
ptrlib/arch/linux/ospath.py
ptrlib/arch/linux/sig.py
ptrlib/arch/linux/syscall.py
ptrlib/arch/windows/__init__.py
ptrlib/arch/windows/ospath.py
ptrlib/binary/__init__.py
ptrlib/binary/encoding/__init__.py
ptrlib/binary/encoding/ansi.py
ptrlib/binary/encoding/bitconv.py
ptrlib/binary/encoding/byteconv.py
ptrlib/binary/encoding/char.py
ptrlib/binary/encoding/dump.py
ptrlib/binary/encoding/table.py
ptrlib/binary/operation/__init__.py
ptrlib/binary/operation/rotate.py
ptrlib/binary/operation/xor.py
ptrlib/binary/packing/__init__.py
ptrlib/binary/packing/chunks.py
ptrlib/binary/packing/flat.py
ptrlib/binary/packing/pack.py
ptrlib/binary/packing/unpack.py
ptrlib/binary/statistics/__init__.py
ptrlib/binary/statistics/statistics.py
ptrlib/connection/__init__.py
ptrlib-3.1.1.dist-info/LICENSE.txt
ptrlib-3.1.1.dist-info/METADATA
ptrlib-3.1.1.dist-info/WHEEL
ptrlib-3.1.1.dist-info/entry_points.txt
ptrlib-3.1.1.dist-info/top_level.txt
ptrlib-3.1.1.dist-info/RECORD
