Metadata-Version: 2.1
Name: ptrlib
Version: 3.1.1
Summary: CTF library
Home-page: https://github.com/ptr-yudai/ptrlib/
Author: ptr-yudai
Author-email: ptr.yudai+dev@gmail.com
Keywords: pwn crypto algorithm
Classifier: License :: OSI Approved :: MIT License
Classifier: Programming Language :: Python :: 3.10
Classifier: Programming Language :: Python :: 3.11
Classifier: Programming Language :: Python :: 3.12
Classifier: Programming Language :: Python :: 3.13
Classifier: Programming Language :: Python :: 3.14
Requires-Python: >=3.10
License-File: LICENSE.txt
Requires-Dist: pycryptodome
Requires-Dist: pywin32; platform_system == "Windows"
